AINetworkDagSdk/__init__.py
AINetworkDagSdk/sdk.py
AINetworkDagSdk/proto/__init__.py
AINetworkDagSdk/proto/ai_network_dag_pb2.py
AINetworkDagSdk/proto/ai_network_dag_pb2_grpc.py
tests/__init__.py
tests/test_sdk.py
ai_network_dag_sdk-0.9.4.dist-info/LICENSE
ai_network_dag_sdk-0.9.4.dist-info/METADATA
ai_network_dag_sdk-0.9.4.dist-info/WHEEL
ai_network_dag_sdk-0.9.4.dist-info/top_level.txt
ai_network_dag_sdk-0.9.4.dist-info/RECORD
